randSelector/__init__.py
randSelector/rand_selector.py
randSelector-1.0.3.dist-info/METADATA
randSelector-1.0.3.dist-info/WHEEL
randSelector-1.0.3.dist-info/top_level.txt
randSelector-1.0.3.dist-info/RECORD
