Metadata-Version: 2.1
Name: randSelector
Version: 1.0.3
Summary: random value selector with associated probability package
Home-page: 
Author: Syed Hamza Rafique
Author-email: hamzah_shah@hotmail.com
License: UNKNOWN
Platform: UNKNOWN
Classifier: Programming Language :: Python :: 3
Classifier: License :: OSI Approved :: MIT License
Classifier: Operating System :: OS Independent
